netfuse/__init__.py
netfuse/config.py
netfuse/errors.py
netfuse/logger.py
netfuse/main.py
netfuse/modules/att.py
netfuse/modules/netgear.py
netfuse/modules/squire.py
NetFuse-0.1.0.dist-info/LICENSE
NetFuse-0.1.0.dist-info/METADATA
NetFuse-0.1.0.dist-info/WHEEL
NetFuse-0.1.0.dist-info/entry_points.txt
NetFuse-0.1.0.dist-info/top_level.txt
NetFuse-0.1.0.dist-info/RECORD
