Metadata-Version: 2.1
Name: NetFuse
Version: 0.1.0
Summary: Python module to dump hostname and IP address mapping for localhost into host file.
Author-email: Vignesh Rao <svignesh1793@gmail.com>
License: MIT License
Project-URL: Homepage, https://github.com/thevickypedia/NetFuse
Project-URL: Docs, https://thevickypedia.github.io/NetFuse
Project-URL: Source, https://github.com/thevickypedia/NetFuse
Project-URL: Bug Tracker, https://github.com/thevickypedia/NetFuse/issues
Project-URL: Release Notes, https://github.com/thevickypedia/NetFuse/blob/main/release_notes.rst
Keywords: localhost,network-synchronization,NetFuse
Classifier: License :: OSI Approved :: MIT License
Classifier: Programming Language :: Python :: 3
Classifier: Development Status :: 5 - Production/Stable
Classifier: Operating System :: MacOS :: MacOS X
Classifier: Operating System :: Microsoft :: Windows
Classifier: Operating System :: POSIX :: Linux
Classifier: Topic :: System :: Networking :: Firewalls
Classifier: Topic :: System :: Networking :: Monitoring
Requires-Python: >=3.8
License-File: LICENSE
Requires-Dist: click>=8.1.7
Provides-Extra: att
Requires-Dist: pandas==2.2.2; extra == "att"
Requires-Dist: lxml==5.3.0; extra == "att"
Requires-Dist: requests>=2.32.3; extra == "att"
Provides-Extra: dev
Requires-Dist: sphinx==5.1.1; extra == "dev"
Requires-Dist: pre-commit; extra == "dev"
Requires-Dist: recommonmark; extra == "dev"
Requires-Dist: gitverse; extra == "dev"
Provides-Extra: netgear
Requires-Dist: pynetgear==0.10.10; extra == "netgear"
